pyadvtools/.python-version
pyadvtools/__init__.py
pyadvtools/pyadvtools.sublime-syntax
pyadvtools/tools.py
pyadvtools/core/__init__.py
pyadvtools/core/check.py
pyadvtools/core/convert.py
pyadvtools/core/delete.py
pyadvtools/core/print.py
pyadvtools/core/sort.py
pyadvtools/core/standard.py
pyadvtools/main/__init__.py
pyadvtools/main/auto_git.py
pyadvtools/main/dict.py
pyadvtools/main/list.py
pyadvtools/main/read_write.py
pyadvtools-0.3.10.dist-info/METADATA
pyadvtools-0.3.10.dist-info/WHEEL
pyadvtools-0.3.10.dist-info/licenses/LICENSE
pyadvtools-0.3.10.dist-info/RECORD
