Metadata-Version: 2.4
Name: pyadvtools
Version: 0.3.10
Summary: pyadvtools
Project-URL: Homepage, https://github.com/Easy-PhD/pyadvtools
Project-URL: Repository, https://github.com/Easy-PhD/pyadvtools
Project-URL: Documentation, https://Easy-PhD.github.io/pyadvtools
Project-URL: Source, https://github.com/Easy-PhD/pyadvtools
Project-URL: Issues, https://github.com/Easy-PhD/pyadvtools/issues
Project-URL: Changelog, https://github.com/Easy-PhD/pyadvtools/releases
Author-email: NextAI <nextartifintell@gmail.com>
Maintainer-email: NextAI <nextartifintell@gmail.com>
License-Expression: GPL-3.0-or-later
License-File: LICENSE
Keywords: Python
Classifier: Operating System :: OS Independent
Classifier: Programming Language :: Python
Classifier: Programming Language :: Python :: 3
Classifier: Programming Language :: Python :: 3.12
Classifier: Programming Language :: Python :: 3.13
Classifier: Programming Language :: Python :: 3.14
Classifier: Topic :: Software Development :: Libraries :: Python Modules
Requires-Python: >=3.12
